zsp_be_sw/__build_num__.py
zsp_be_sw/__init__.py
zsp_be_sw/__version__.py
zsp_be_sw/core.cpython-311-x86_64-linux-gnu.so
zsp_be_sw/libzsp-be-sw.so
zsp_be_sw/share/include/zsp/be/sw/FactoryExt.h
zsp_be_sw/share/include/zsp/be/sw/IContext.h
zsp_be_sw/share/include/zsp/be/sw/IFactory.h
zsp_be_sw/share/include/zsp/be/sw/IFunctionInfo.h
zsp_be_sw/share/include/zsp/be/sw/IFunctionMap.h
zsp_be_sw/share/include/zsp/be/sw/IGeneratorEvalIterator.h
zsp_be_sw/share/include/zsp/be/sw/IGeneratorFunctions.h
zsp_be_sw/share/include/zsp/be/sw/IGeneratorUnrolledTrace.h
zsp_be_sw/share/include/zsp/be/sw/IMethodCallFactoryAssocData.h
zsp_be_sw/share/include/zsp/be/sw/INameMap.h
zsp_be_sw/share/include/zsp/be/sw/IOutput.h
zsp_be_sw/share/include/zsp/be/sw/IOutputStr.h
zsp_be_sw/share/include/zsp/be/sw/impl/MethodCallFactoryAssocDataBase.h
zsp_be_sw/share/include/zsp/esw/zsp_esw_support.h
zuspec_be_sw-0.0.5.dist-info/LICENSE
zuspec_be_sw-0.0.5.dist-info/METADATA
zuspec_be_sw-0.0.5.dist-info/WHEEL
zuspec_be_sw-0.0.5.dist-info/top_level.txt
zuspec_be_sw-0.0.5.dist-info/RECORD
