Metadata-Version: 2.2
Name: zuspec-be-sw
Version: 0.0.5
Summary: Backend library to generate software output
Home-page: https://github.com/zuspec/zuspec-be-sw
Author: Matthew Ballance
Author-email: matt.ballance@gmail.com
License: Apache 2.0
Keywords: SystemVerilog,Verilog,RTL,Python
License-File: LICENSE
Requires-Dist: ciostream
Requires-Dist: zuspec-arl-dm
Requires-Dist: vsc-dm
Requires-Dist: debug-mgr
Dynamic: author
Dynamic: author-email
Dynamic: description
Dynamic: home-page
Dynamic: keywords
Dynamic: license
Dynamic: requires-dist
Dynamic: summary
